nyahentai/__init__.py
nyahentai/entities/__init__.py
nyahentai/entities/doujin.py
nyahentai/entities/links.py
nyahentai/entities/page.py
Nyahentai_API-1.0.0.dist-info/LICENSE
Nyahentai_API-1.0.0.dist-info/METADATA
Nyahentai_API-1.0.0.dist-info/WHEEL
Nyahentai_API-1.0.0.dist-info/top_level.txt
Nyahentai_API-1.0.0.dist-info/RECORD
