Metadata-Version: 2.1
Name: Nyahentai-API
Version: 1.0.0
Summary: Nyahentai Python API made using webscraping.
Home-page: https://github.com/AlexandreSenpai/Nyahentai-API
Author: AlexandreSenpai
Author-email: alexandrebsramos@hotmail.com
License: MIT
Keywords: nyahentai hentai AlexandreSenpai
Platform: UNKNOWN
Classifier: Programming Language :: Python :: 3
Classifier: License :: OSI Approved :: MIT License
Classifier: Operating System :: OS Independent
Requires-Dist: requests
Requires-Dist: beautifulsoup4
